connectonion/__init__.py
connectonion/address.py
connectonion/console.py
connectonion/llm_do.py
connectonion/logger.py
connectonion/prompts.py
connectonion/transcribe.py
connectonion/cli/__init__.py
connectonion/cli/docs.md
connectonion/cli/main.py
connectonion/cli/browser_agent/__init__.py
connectonion/cli/browser_agent/browser.py
connectonion/cli/browser_agent/element_finder.py
connectonion/cli/browser_agent/highlight_screenshot.py
connectonion/cli/browser_agent/prompt.md
connectonion/cli/browser_agent/scroll.py
connectonion/cli/browser_agent/prompts/element_matcher.md
connectonion/cli/browser_agent/prompts/form_filler.md
connectonion/cli/browser_agent/prompts/scroll_strategy.md
connectonion/cli/browser_agent/scripts/extract_elements.js
connectonion/cli/co_ai/__init__.py
connectonion/cli/co_ai/agent.py
connectonion/cli/co_ai/context.py
connectonion/cli/co_ai/main.py
connectonion/cli/co_ai/sessions.py
connectonion/cli/co_ai/agents/__init__.py
connectonion/cli/co_ai/agents/registry.py
connectonion/cli/co_ai/commands/__init__.py
connectonion/cli/co_ai/commands/compact.py
connectonion/cli/co_ai/commands/cost.py
connectonion/cli/co_ai/commands/export.py
connectonion/cli/co_ai/commands/help.py
connectonion/cli/co_ai/commands/init.py
connectonion/cli/co_ai/commands/sessions.py
connectonion/cli/co_ai/commands/tasks.py
connectonion/cli/co_ai/commands/undo.py
connectonion/cli/co_ai/plugins/__init__.py
connectonion/cli/co_ai/plugins/system_reminder.py
connectonion/cli/co_ai/prompts/assembler.py
connectonion/cli/co_ai/prompts/main.md
connectonion/cli/co_ai/prompts/summarization.md
connectonion/cli/co_ai/prompts/workflow.md
connectonion/cli/co_ai/prompts/agents/explore.md
connectonion/cli/co_ai/prompts/agents/plan.md
connectonion/cli/co_ai/prompts/connectonion/README.md
connectonion/cli/co_ai/prompts/connectonion/api.md
connectonion/cli/co_ai/prompts/connectonion/co-directory-structure.md
connectonion/cli/co_ai/prompts/connectonion/connectonion.md
connectonion-0.6.4.dist-info/METADATA
connectonion-0.6.4.dist-info/WHEEL
connectonion-0.6.4.dist-info/entry_points.txt
connectonion-0.6.4.dist-info/RECORD
