Metadata-Version: 2.4
Name: connectonion
Version: 0.6.4
Summary: A simple Python framework for creating AI agents with behavior tracking
Project-URL: Homepage, https://github.com/openonion/connectonion
Project-URL: Documentation, https://docs.connectonion.com
Project-URL: Repository, https://github.com/openonion/connectonion
Project-URL: Bug Tracker, https://github.com/openonion/connectonion/issues
Author-email: ConnectOnion Team <pypi@connectonion.com>
License: MIT
Keywords: agent,ai,automation,breakpoints,debugging,interactive-debugging,llm,openai,tools,xray
Classifier: Development Status :: 5 - Production/Stable
Classifier: Intended Audience :: Developers
Classifier: License :: OSI Approved :: MIT License
Classifier: Operating System :: OS Independent
Classifier: Programming Language :: Python :: 3
Classifier: Programming Language :: Python :: 3.10
Classifier: Programming Language :: Python :: 3.11
Classifier: Programming Language :: Python :: 3.12
Classifier: Programming Language :: Python :: 3.13
Classifier: Topic :: Scientific/Engineering :: Artificial Intelligence
Classifier: Topic :: Software Development :: Libraries :: Python Modules
Requires-Python: >=3.10
Requires-Dist: anthropic>=0.18.0
Requires-Dist: beautifulsoup4>=4.12.0
Requires-Dist: click>=8.0.0
Requires-Dist: google-api-python-client>=2.0.0
Requires-Dist: google-auth>=2.0.0
Requires-Dist: httpx>=0.24.0
Requires-Dist: litellm>=1.0.0
Requires-Dist: mnemonic>=0.20
Requires-Dist: openai>=1.0.0
Requires-Dist: playwright>=1.40.0
Requires-Dist: pydantic>=2.0.0
Requires-Dist: pyjwt>=2.0.0
Requires-Dist: pynacl>=1.5.0
Requires-Dist: python-dotenv>=1.0.0
Requires-Dist: pyyaml>=6.0.0
Requires-Dist: questionary>=2.0.0
Requires-Dist: requests>=2.25.0
Requires-Dist: rich>=13.0.0
Requires-Dist: textual-autocomplete>=3.0.0
Requires-Dist: textual>=0.86.0
Requires-Dist: toml>=0.10.2
Requires-Dist: typer>=0.20.0
Requires-Dist: uvicorn>=0.20.0
Requires-Dist: websockets>=11.0.0
Provides-Extra: dev
Requires-Dist: pytest-asyncio>=0.21.0; extra == 'dev'
Requires-Dist: pytest-cov>=4.0.0; extra == 'dev'
Requires-Dist: pytest>=7.0.0; extra == 'dev'
